{
  "R0072": {
    "title": "员工贪腐",
    "definition": "员工贪腐是指员工在工作场所中以不正当手段谋取个人私利、滥用职权、收受贿赂或参与腐败活动的行为。",
    "description": "这可能包括虚报报销、向供应商索取回扣、滥用公司资源、贿赂或参与其他腐败行为。",
    "complexity": "初级",
    "influence": "员工贪腐的危害包括损害公司的声誉、破坏内部信任、影响工作效率、导致资源浪费、增加合规性风险，最终可能引发法律责任和经济损失。",
    "avoidances": [
      "A0043",
      "A0019",
      "A0051",
      "A0052",
      "A0020-002",
      "A0044"
    ],
    "references": [],
    "updated": "2024-01-15"
  },
  "R0072-001": {
    "title": "内外勾结(内鬼)",
    "definition": "员工内外勾结是指公司内部员工与外部个人或组织合谋，以实施欺诈、贪污、行贿或其他不正当行为，违反公司的利益和法规。",
    "description": "行为或场景包括员工与供应商串通进行虚报开支、腐败交易、内外勾结进行欺诈活动等。",
    "complexity": "初级",
    "influence": "可能导致公司经济损失、声誉受损，同时增加合规性风险，对公司的稳健经营构成严重威胁。",
    "avoidances": [
      "A0043",
      "A0019",
      "A0051",
      "A0052",
      "A0020-002",
      "A0044"
    ],
    "references": [],
    "updated": "2024-01-15"
  }
}