{
  "TA0034": {
    "title": "职业打假人",
    "description": "职业打假人是指利用《消费者权益保护法》《食品安全法》等法律法规中的惩罚性赔偿条款，批量购买存在标签瑕疵、宣传不规范等问题的商品后发起索赔以牟利的群体。这是中国电商领域特有的灰产现象。主要行为特征包括：①精准选品：专门搜索商品描述中的违规用语（如\"最佳\"\"第一\"等绝对化用语）、标签不规范、资质缺失等问题商品。②批量下单：对同一问题商品进行多次小额购买，每笔订单独立发起索赔以最大化赔偿金额。③证据固化：使用公证、录屏等方式固化购买和商品问题的证据链。④多渠道施压：同时通过平台投诉、市场监管部门举报、法院起诉等多渠道向商家施压。⑤团队化运作：形成选品、购买、投诉、诉讼的流水线作业模式。⑥知识库共享：在社群中分享索赔话术、成功案例和目标商品信息。职业打假人的行为处于法律灰色地带，部分地区法院已对职业打假的牟利性索赔进行限制。",
    "references": [
      {
        "title": "消费者权益保护法",
        "link": "http://www.npc.gov.cn/"
      },
      {
        "title": "最高人民法院关于审理食品药品纠纷案件适用法律若干问题的规定",
        "link": "https://www.court.gov.cn/"
      }
    ],
    "buildAttackTools": [],
    "useAttackTools": ["AT0005", "AT0003"],
    "couseRisks": ["R0139", "R0054", "R0056", "R0071"],
    "updated": "2026-02-27"
  }
}
